<!DOCTYPE ui:UiBinder SYSTEM "http://dl.google.com/gwt/DTD/xhtml.ent">
<ui:UiBinder xmlns:ui="urn:ui:com.google.gwt.uibinder"	xmlns:g="urn:import:com.google.gwt.user.client.ui"
		xmlns:dp="urn:import:com.sap.sailing.gwt.home.desktop.partials">
	<ui:with field="i18n" type="com.sap.sailing.gwt.ui.client.StringMessages" />
	<ui:with field="res" type="com.sap.sailing.gwt.common.client.SharedResources" />
	<ui:with field="local_res" type="com.sap.sailing.gwt.home.desktop.partials.regattacompetition.RegattaCompetitionResources" />
	<div class="{local_res.css.fleet_races_race}">
		<div class="{local_res.css.fleet_races_race_name}" ui:field="raceNameUi"></div>
		<div class="{local_res.css.fleet_races_race_info} {res.mediaCss.hideonsmall}">
			<div class="{local_res.css.fleet_races_race_state}" ui:field="raceStateUi"></div>
			<div class="{local_res.css.fleet_races_race_date}" ui:field="raceDateUi"></div>
		</div>
	</div>
</ui:UiBinder>